casualconsole-0.1.data/scripts/casualconsole
console/__init__.py
console/app.py
console/assets/__init__.py
console/assets/assets.py
console/config/__init__.py
console/config/config.py
console/config/users.ini
console/routes/__init__.py
console/routes/api.py
console/routes/open.py
console/routes/routes.py
console/routes/views.py
console/state/__init__.py
console/state/gateway.py
console/state/group.py
console/state/information.py
console/state/server.py
console/state/service.py
console/state/transaction.py
console/state/update.py
console/static/favicon.ico
console/static/font/SourceCodePro-Black.ttf
console/static/font/SourceCodePro-BlackItalic.ttf
console/static/font/SourceCodePro-Bold.ttf
console/static/font/SourceCodePro-BoldItalic.ttf
console/static/font/SourceCodePro-ExtraLight.ttf
console/static/font/SourceCodePro-ExtraLightItalic.ttf
console/static/font/SourceCodePro-Italic.ttf
console/static/font/SourceCodePro-Light.ttf
console/static/font/SourceCodePro-LightItalic.ttf
console/static/font/SourceCodePro-Medium.ttf
console/static/font/SourceCodePro-MediumItalic.ttf
console/static/font/SourceCodePro-Regular.ttf
console/static/font/SourceCodePro-SemiBold.ttf
console/static/font/SourceCodePro-SemiBoldItalic.ttf
console/static/gen/casual.css
console/static/gen/casual.js
console/static/gen/lib.js
console/static/gen/css/casual.css
console/static/img/bars.svg
console/static/img/casual box left BW.svg
console/static/img/casual box right BW.svg
console/static/img/casual vertical BW.svg
console/static/img/casual word BW.svg
console/static/img/casual_box_left_BW.svg
console/static/img/casual_left_BW.svg
console/static/img/casual_main_logo.png
console/static/img/casual_symbol_BW.svg
console/static/img/casual_vertical_BW.svg
console/static/img/collapse-arrow.svg
console/static/img/executables.svg
console/static/img/gateways.svg
console/static/img/groups.svg
console/static/img/left-arrow-single.svg
console/static/img/right-arrow-single.svg
console/static/img/servers.svg
casualconsole-0.1.dist-info/METADATA
casualconsole-0.1.dist-info/WHEEL
casualconsole-0.1.dist-info/top_level.txt
casualconsole-0.1.dist-info/RECORD
